LICENSE
MANIFEST.in
README.md
setup.py
src/detach.c
src/jetsam.py
src/log.c
src/log.h
src/jetsam.egg-info/PKG-INFO
src/jetsam.egg-info/SOURCES.txt
src/jetsam.egg-info/dependency_links.txt
src/jetsam.egg-info/top_level.txt