Metadata-Version: 2.1
Name: jetsam
Version: 0.2.1
Summary: Jettison functions with jetsam!
Author: Tony B
Author-email: tony@ballast.dev
License: MIT
Project-URL: Source Code, https://gitlab.com/ballast-dev/jetsam
Requires-Python: >=3.8
License-File: LICENSE
